[
  {
    "USDT-0": {
      "index": 1,
      "usdt_amount": 4.71,
      "usdt_supply": 1000,
      "total-borrowed": 0,
      "rate": 0.005,
      "hourly-rate": 5.723443223443223e-7,
      "liabilities": 0,
      "timestamp": 1717276338,
      "liability_charge": 0
    },
    "USDT-1": {
      "index": 1,
      "usdt_amount": 995.29,
      "usdt_supply": 1000,
      "total-borrowed": 0,
      "rate": 0.005,
      "hourly-rate": 5.723443223443223e-7,
      "liabilities": 0,
      "timestamp": 1717276338,
      "earningreate_charge": 0
    },
    "USDT-2": {
      "index": 1,
      "usdt_amount": 0,
      "usdt_supply": 1000,
      "total-borrowed": 0,
      "rate": 0.005,
      "hourly-rate": 5.723443223443223e-7,
      "liabilities": 0,
      "timestamp": 1717276338
    },
    "REXE-0": {
      "index": 1,
      "rexe_amount": 999,
      "rexe_supply": 1000,
      "total-borrowed": 0,
      "rate": 0.005,
      "hourly-rate": 5.723443223443223e-7,
      "liabilities": 0,
      "timestamp": 1717276338
    },
    "REXE-1": {
      "index": 1,
      "rexe_amount": 1,
      "rexe_supply": 1000,
      "total-borrowed": 0,
      "rate": 0.005,
      "hourly-rate": 5.723443223443223e-7,
      "liabilities": 0,
      "timestamp": 1717276338
    },
    "REXE-2": {
      "index": 1,
      "rexe_amount": 0,
      "rexe_supply": 1000,
      "total-borrowed": 0,
      "rate": 0.005,
      "hourly-rate": 5.723443223443223e-7,
      "liabilities": 0,
      "timestamp": 1717276338
    }
  },
  {
    "USDT-0": {
      "index": 1,
      "usdt_amount": 9.42,
      "usdt_supply": 1000,
      "total-borrowed": 0,
      "rate": 0.005,
      "hourly-rate": 5.723443223443223e-7,
      "liabilities": 0,
      "timestamp": 1717276348,
      "liability_charge": 0
    },
    "USDT-1": {
      "index": 1,
      "usdt_amount": 990.58,
      "usdt_supply": 1000,
      "total-borrowed": 0,
      "rate": 0.005,
      "hourly-rate": 5.723443223443223e-7,
      "liabilities": 0,
      "timestamp": 1717276348,
      "earningreate_charge": 0
    },
    "USDT-2": {
      "index": 1,
      "usdt_amount": 0,
      "usdt_supply": 1000,
      "total-borrowed": 0,
      "rate": 0.005,
      "hourly-rate": 5.723443223443223e-7,
      "liabilities": 0,
      "timestamp": 1717276348
    },
    "REXE-0": {
      "index": 1,
      "rexe_amount": 998,
      "rexe_supply": 1000,
      "total-borrowed": 0,
      "rate": 0.005,
      "hourly-rate": 5.723443223443223e-7,
      "liabilities": 0,
      "timestamp": 1717276348
    },
    "REXE-1": {
      "index": 1,
      "rexe_amount": 2,
      "rexe_supply": 1000,
      "total-borrowed": 0,
      "rate": 0.005,
      "hourly-rate": 5.723443223443223e-7,
      "liabilities": 0,
      "timestamp": 1717276348
    },
    "REXE-2": {
      "index": 1,
      "rexe_amount": 0,
      "rexe_supply": 1000,
      "total-borrowed": 0,
      "rate": 0.005,
      "hourly-rate": 5.723443223443223e-7,
      "liabilities": 0,
      "timestamp": 1717276348
    }
  },
  {
    "USDT-0": {
      "index": 1,
      "usdt_amount": 14.13,
      "usdt_supply": 1000,
      "total-borrowed": 0,
      "rate": 0.005,
      "hourly-rate": 5.723443223443223e-7,
      "liabilities": 0,
      "timestamp": 1717276358,
      "liability_charge": 0
    },
    "USDT-1": {
      "index": 1,
      "usdt_amount": 985.8700000000001,
      "usdt_supply": 1000,
      "total-borrowed": 0,
      "rate": 0.005,
      "hourly-rate": 5.723443223443223e-7,
      "liabilities": 0,
      "timestamp": 1717276358,
      "earningreate_charge": 0
    },
    "USDT-2": {
      "index": 1,
      "usdt_amount": 0,
      "usdt_supply": 1000,
      "total-borrowed": 0,
      "rate": 0.005,
      "hourly-rate": 5.723443223443223e-7,
      "liabilities": 0,
      "timestamp": 1717276358
    },
    "REXE-0": {
      "index": 1,
      "rexe_amount": 997,
      "rexe_supply": 1000,
      "total-borrowed": 0,
      "rate": 0.005,
      "hourly-rate": 5.723443223443223e-7,
      "liabilities": 0,
      "timestamp": 1717276358
    },
    "REXE-1": {
      "index": 1,
      "rexe_amount": 3,
      "rexe_supply": 1000,
      "total-borrowed": 0,
      "rate": 0.005,
      "hourly-rate": 5.723443223443223e-7,
      "liabilities": 0,
      "timestamp": 1717276358
    },
    "REXE-2": {
      "index": 1,
      "rexe_amount": 0,
      "rexe_supply": 1000,
      "total-borrowed": 0,
      "rate": 0.005,
      "hourly-rate": 5.723443223443223e-7,
      "liabilities": 0,
      "timestamp": 1717276358
    }
  },
  {
    "USDT-0": {
      "index": 1,
      "usdt_amount": 18.84,
      "usdt_supply": 1000,
      "total-borrowed": 0,
      "rate": 0.005,
      "hourly-rate": 5.723443223443223e-7,
      "liabilities": 0,
      "timestamp": 1717276368,
      "liability_charge": 0
    },
    "USDT-1": {
      "index": 1,
      "usdt_amount": 981.16,
      "usdt_supply": 1000,
      "total-borrowed": 0,
      "rate": 0.005,
      "hourly-rate": 5.723443223443223e-7,
      "liabilities": 0,
      "timestamp": 1717276368,
      "earningreate_charge": 0
    },
    "USDT-2": {
      "index": 1,
      "usdt_amount": 0,
      "usdt_supply": 1000,
      "total-borrowed": 0,
      "rate": 0.005,
      "hourly-rate": 5.723443223443223e-7,
      "liabilities": 0,
      "timestamp": 1717276368
    },
    "REXE-0": {
      "index": 1,
      "rexe_amount": 996,
      "rexe_supply": 1000,
      "total-borrowed": 0,
      "rate": 0.005,
      "hourly-rate": 5.723443223443223e-7,
      "liabilities": 0,
      "timestamp": 1717276368
    },
    "REXE-1": {
      "index": 1,
      "rexe_amount": 4,
      "rexe_supply": 1000,
      "total-borrowed": 0,
      "rate": 0.005,
      "hourly-rate": 5.723443223443223e-7,
      "liabilities": 0,
      "timestamp": 1717276368
    },
    "REXE-2": {
      "index": 1,
      "rexe_amount": 0,
      "rexe_supply": 1000,
      "total-borrowed": 0,
      "rate": 0.005,
      "hourly-rate": 5.723443223443223e-7,
      "liabilities": 0,
      "timestamp": 1717276368
    }
  },
  {
    "USDT-0": {
      "index": 1,
      "usdt_amount": 23.55,
      "usdt_supply": 1000,
      "total-borrowed": 0,
      "rate": 0.005,
      "hourly-rate": 5.723443223443223e-7,
      "liabilities": 0,
      "timestamp": 1717276378,
      "liability_charge": 0
    },
    "USDT-1": {
      "index": 1,
      "usdt_amount": 976.4499999999999,
      "usdt_supply": 1000,
      "total-borrowed": 0,
      "rate": 0.005,
      "hourly-rate": 5.723443223443223e-7,
      "liabilities": 0,
      "timestamp": 1717276378,
      "earningreate_charge": 0
    },
    "USDT-2": {
      "index": 1,
      "usdt_amount": 0,
      "usdt_supply": 1000,
      "total-borrowed": 0,
      "rate": 0.005,
      "hourly-rate": 5.723443223443223e-7,
      "liabilities": 0,
      "timestamp": 1717276378
    },
    "REXE-0": {
      "index": 1,
      "rexe_amount": 995,
      "rexe_supply": 1000,
      "total-borrowed": 0,
      "rate": 0.005,
      "hourly-rate": 5.723443223443223e-7,
      "liabilities": 0,
      "timestamp": 1717276378
    },
    "REXE-1": {
      "index": 1,
      "rexe_amount": 5,
      "rexe_supply": 1000,
      "total-borrowed": 0,
      "rate": 0.005,
      "hourly-rate": 5.723443223443223e-7,
      "liabilities": 0,
      "timestamp": 1717276378
    },
    "REXE-2": {
      "index": 1,
      "rexe_amount": 0,
      "rexe_supply": 1000,
      "total-borrowed": 0,
      "rate": 0.005,
      "hourly-rate": 5.723443223443223e-7,
      "liabilities": 0,
      "timestamp": 1717276378
    }
  },
  {
    "USDT-0": {
      "index": 1,
      "usdt_amount": 28.26,
      "usdt_supply": 1000,
      "total-borrowed": 0,
      "rate": 0.005,
      "hourly-rate": 5.723443223443223e-7,
      "liabilities": 0,
      "timestamp": 1717276388,
      "liability_charge": 0
    },
    "USDT-1": {
      "index": 1,
      "usdt_amount": 971.74,
      "usdt_supply": 1000,
      "total-borrowed": 0,
      "rate": 0.005,
      "hourly-rate": 5.723443223443223e-7,
      "liabilities": 0,
      "timestamp": 1717276388,
      "earningreate_charge": 0
    },
    "USDT-2": {
      "index": 1,
      "usdt_amount": 0,
      "usdt_supply": 1000,
      "total-borrowed": 0,
      "rate": 0.005,
      "hourly-rate": 5.723443223443223e-7,
      "liabilities": 0,
      "timestamp": 1717276388
    },
    "REXE-0": {
      "index": 1,
      "rexe_amount": 994,
      "rexe_supply": 1000,
      "total-borrowed": 0,
      "rate": 0.005,
      "hourly-rate": 5.723443223443223e-7,
      "liabilities": 0,
      "timestamp": 1717276388
    },
    "REXE-1": {
      "index": 1,
      "rexe_amount": 6,
      "rexe_supply": 1000,
      "total-borrowed": 0,
      "rate": 0.005,
      "hourly-rate": 5.723443223443223e-7,
      "liabilities": 0,
      "timestamp": 1717276388
    },
    "REXE-2": {
      "index": 1,
      "rexe_amount": 0,
      "rexe_supply": 1000,
      "total-borrowed": 0,
      "rate": 0.005,
      "hourly-rate": 5.723443223443223e-7,
      "liabilities": 0,
      "timestamp": 1717276388
    }
  },
  {
    "USDT-0": {
      "index": 1,
      "usdt_amount": 32.97,
      "usdt_supply": 1000,
      "total-borrowed": 0,
      "rate": 0.005,
      "hourly-rate": 5.723443223443223e-7,
      "liabilities": 0,
      "timestamp": 1717276398,
      "liability_charge": 0
    },
    "USDT-1": {
      "index": 1,
      "usdt_amount": 967.0300000000001,
      "usdt_supply": 1000,
      "total-borrowed": 0,
      "rate": 0.005,
      "hourly-rate": 5.723443223443223e-7,
      "liabilities": 0,
      "timestamp": 1717276398,
      "earningreate_charge": 0
    },
    "USDT-2": {
      "index": 1,
      "usdt_amount": 0,
      "usdt_supply": 1000,
      "total-borrowed": 0,
      "rate": 0.005,
      "hourly-rate": 5.723443223443223e-7,
      "liabilities": 0,
      "timestamp": 1717276398
    },
    "REXE-0": {
      "index": 1,
      "rexe_amount": 993,
      "rexe_supply": 1000,
      "total-borrowed": 0,
      "rate": 0.005,
      "hourly-rate": 5.723443223443223e-7,
      "liabilities": 0,
      "timestamp": 1717276398
    },
    "REXE-1": {
      "index": 1,
      "rexe_amount": 7,
      "rexe_supply": 1000,
      "total-borrowed": 0,
      "rate": 0.005,
      "hourly-rate": 5.723443223443223e-7,
      "liabilities": 0,
      "timestamp": 1717276398
    },
    "REXE-2": {
      "index": 1,
      "rexe_amount": 0,
      "rexe_supply": 1000,
      "total-borrowed": 0,
      "rate": 0.005,
      "hourly-rate": 5.723443223443223e-7,
      "liabilities": 0,
      "timestamp": 1717276398
    }
  },
  {
    "USDT-0": {
      "index": 1,
      "usdt_amount": 37.68,
      "usdt_supply": 1000,
      "total-borrowed": 0,
      "rate": 0.005,
      "hourly-rate": 5.723443223443223e-7,
      "liabilities": 0,
      "timestamp": 1717276408,
      "liability_charge": 0
    },
    "USDT-1": {
      "index": 1,
      "usdt_amount": 962.32,
      "usdt_supply": 1000,
      "total-borrowed": 0,
      "rate": 0.005,
      "hourly-rate": 5.723443223443223e-7,
      "liabilities": 0,
      "timestamp": 1717276408,
      "earningreate_charge": 0
    },
    "USDT-2": {
      "index": 1,
      "usdt_amount": 0,
      "usdt_supply": 1000,
      "total-borrowed": 0,
      "rate": 0.005,
      "hourly-rate": 5.723443223443223e-7,
      "liabilities": 0,
      "timestamp": 1717276408
    },
    "REXE-0": {
      "index": 1,
      "rexe_amount": 992,
      "rexe_supply": 1000,
      "total-borrowed": 0,
      "rate": 0.005,
      "hourly-rate": 5.723443223443223e-7,
      "liabilities": 0,
      "timestamp": 1717276408
    },
    "REXE-1": {
      "index": 1,
      "rexe_amount": 8,
      "rexe_supply": 1000,
      "total-borrowed": 0,
      "rate": 0.005,
      "hourly-rate": 5.723443223443223e-7,
      "liabilities": 0,
      "timestamp": 1717276408
    },
    "REXE-2": {
      "index": 1,
      "rexe_amount": 0,
      "rexe_supply": 1000,
      "total-borrowed": 0,
      "rate": 0.005,
      "hourly-rate": 5.723443223443223e-7,
      "liabilities": 0,
      "timestamp": 1717276408
    }
  },
  {
    "USDT-0": {
      "index": 1,
      "usdt_amount": 42.39,
      "usdt_supply": 1000,
      "total-borrowed": 0,
      "rate": 0.005,
      "hourly-rate": 5.723443223443223e-7,
      "liabilities": 0,
      "timestamp": 1717276418,
      "liability_charge": 0
    },
    "USDT-1": {
      "index": 1,
      "usdt_amount": 957.6099999999999,
      "usdt_supply": 1000,
      "total-borrowed": 0,
      "rate": 0.005,
      "hourly-rate": 5.723443223443223e-7,
      "liabilities": 0,
      "timestamp": 1717276418,
      "earningreate_charge": 0
    },
    "USDT-2": {
      "index": 1,
      "usdt_amount": 0,
      "usdt_supply": 1000,
      "total-borrowed": 0,
      "rate": 0.005,
      "hourly-rate": 5.723443223443223e-7,
      "liabilities": 0,
      "timestamp": 1717276418
    },
    "REXE-0": {
      "index": 1,
      "rexe_amount": 991,
      "rexe_supply": 1000,
      "total-borrowed": 0,
      "rate": 0.005,
      "hourly-rate": 5.723443223443223e-7,
      "liabilities": 0,
      "timestamp": 1717276418
    },
    "REXE-1": {
      "index": 1,
      "rexe_amount": 9,
      "rexe_supply": 1000,
      "total-borrowed": 0,
      "rate": 0.005,
      "hourly-rate": 5.723443223443223e-7,
      "liabilities": 0,
      "timestamp": 1717276418
    },
    "REXE-2": {
      "index": 1,
      "rexe_amount": 0,
      "rexe_supply": 1000,
      "total-borrowed": 0,
      "rate": 0.005,
      "hourly-rate": 5.723443223443223e-7,
      "liabilities": 0,
      "timestamp": 1717276418
    }
  },
  {
    "USDT-0": {
      "index": 1,
      "usdt_amount": 47.1,
      "usdt_supply": 1000,
      "total-borrowed": 0,
      "rate": 0.005,
      "hourly-rate": 5.723443223443223e-7,
      "liabilities": 0,
      "timestamp": 1717276428,
      "liability_charge": 0
    },
    "USDT-1": {
      "index": 1,
      "usdt_amount": 952.9,
      "usdt_supply": 1000,
      "total-borrowed": 0,
      "rate": 0.005,
      "hourly-rate": 5.723443223443223e-7,
      "liabilities": 0,
      "timestamp": 1717276428,
      "earningreate_charge": 0
    },
    "USDT-2": {
      "index": 1,
      "usdt_amount": 0,
      "usdt_supply": 1000,
      "total-borrowed": 0,
      "rate": 0.005,
      "hourly-rate": 5.723443223443223e-7,
      "liabilities": 0,
      "timestamp": 1717276428
    },
    "REXE-0": {
      "index": 1,
      "rexe_amount": 990,
      "rexe_supply": 1000,
      "total-borrowed": 0,
      "rate": 0.005,
      "hourly-rate": 5.723443223443223e-7,
      "liabilities": 0,
      "timestamp": 1717276428
    },
    "REXE-1": {
      "index": 1,
      "rexe_amount": 10,
      "rexe_supply": 1000,
      "total-borrowed": 0,
      "rate": 0.005,
      "hourly-rate": 5.723443223443223e-7,
      "liabilities": 0,
      "timestamp": 1717276428
    },
    "REXE-2": {
      "index": 1,
      "rexe_amount": 0,
      "rexe_supply": 1000,
      "total-borrowed": 0,
      "rate": 0.005,
      "hourly-rate": 5.723443223443223e-7,
      "liabilities": 0,
      "timestamp": 1717276428
    }
  },
  {
    "USDT-0": {
      "index": 1,
      "usdt_amount": 51.81,
      "usdt_supply": 1000,
      "total-borrowed": 0,
      "rate": 0.005,
      "hourly-rate": 5.723443223443223e-7,
      "liabilities": 0,
      "timestamp": 1717276438,
      "liability_charge": 0
    },
    "USDT-1": {
      "index": 1,
      "usdt_amount": 948.19,
      "usdt_supply": 1000,
      "total-borrowed": 0,
      "rate": 0.005,
      "hourly-rate": 5.723443223443223e-7,
      "liabilities": 0,
      "timestamp": 1717276438,
      "earningreate_charge": 0
    },
    "USDT-2": {
      "index": 1,
      "usdt_amount": 0,
      "usdt_supply": 1000,
      "total-borrowed": 0,
      "rate": 0.005,
      "hourly-rate": 5.723443223443223e-7,
      "liabilities": 0,
      "timestamp": 1717276438
    },
    "REXE-0": {
      "index": 1,
      "rexe_amount": 989,
      "rexe_supply": 1000,
      "total-borrowed": 0,
      "rate": 0.005,
      "hourly-rate": 5.723443223443223e-7,
      "liabilities": 0,
      "timestamp": 1717276438
    },
    "REXE-1": {
      "index": 1,
      "rexe_amount": 11,
      "rexe_supply": 1000,
      "total-borrowed": 0,
      "rate": 0.005,
      "hourly-rate": 5.723443223443223e-7,
      "liabilities": 0,
      "timestamp": 1717276438
    },
    "REXE-2": {
      "index": 1,
      "rexe_amount": 0,
      "rexe_supply": 1000,
      "total-borrowed": 0,
      "rate": 0.005,
      "hourly-rate": 5.723443223443223e-7,
      "liabilities": 0,
      "timestamp": 1717276438
    }
  },
  {
    "USDT-0": {
      "index": 1,
      "usdt_amount": 56.52,
      "usdt_supply": 1000,
      "total-borrowed": 0,
      "rate": 0.005,
      "hourly-rate": 5.723443223443223e-7,
      "liabilities": 0,
      "timestamp": 1717276448,
      "liability_charge": 0
    },
    "USDT-1": {
      "index": 1,
      "usdt_amount": 943.48,
      "usdt_supply": 1000,
      "total-borrowed": 0,
      "rate": 0.005,
      "hourly-rate": 5.723443223443223e-7,
      "liabilities": 0,
      "timestamp": 1717276448,
      "earningreate_charge": 0
    },
    "USDT-2": {
      "index": 1,
      "usdt_amount": 0,
      "usdt_supply": 1000,
      "total-borrowed": 0,
      "rate": 0.005,
      "hourly-rate": 5.723443223443223e-7,
      "liabilities": 0,
      "timestamp": 1717276448
    },
    "REXE-0": {
      "index": 1,
      "rexe_amount": 988,
      "rexe_supply": 1000,
      "total-borrowed": 0,
      "rate": 0.005,
      "hourly-rate": 5.723443223443223e-7,
      "liabilities": 0,
      "timestamp": 1717276448
    },
    "REXE-1": {
      "index": 1,
      "rexe_amount": 12,
      "rexe_supply": 1000,
      "total-borrowed": 0,
      "rate": 0.005,
      "hourly-rate": 5.723443223443223e-7,
      "liabilities": 0,
      "timestamp": 1717276448
    },
    "REXE-2": {
      "index": 1,
      "rexe_amount": 0,
      "rexe_supply": 1000,
      "total-borrowed": 0,
      "rate": 0.005,
      "hourly-rate": 5.723443223443223e-7,
      "liabilities": 0,
      "timestamp": 1717276448
    }
  },
  {
    "USDT-0": {
      "index": 1,
      "usdt_amount": 61.23,
      "usdt_supply": 1000,
      "total-borrowed": 0,
      "rate": 0.005,
      "hourly-rate": 5.723443223443223e-7,
      "liabilities": 0,
      "timestamp": 1717276458,
      "liability_charge": 0
    },
    "USDT-1": {
      "index": 1,
      "usdt_amount": 938.77,
      "usdt_supply": 1000,
      "total-borrowed": 0,
      "rate": 0.005,
      "hourly-rate": 5.723443223443223e-7,
      "liabilities": 0,
      "timestamp": 1717276458,
      "earningreate_charge": 0
    },
    "USDT-2": {
      "index": 1,
      "usdt_amount": 0,
      "usdt_supply": 1000,
      "total-borrowed": 0,
      "rate": 0.005,
      "hourly-rate": 5.723443223443223e-7,
      "liabilities": 0,
      "timestamp": 1717276458
    },
    "REXE-0": {
      "index": 1,
      "rexe_amount": 987,
      "rexe_supply": 1000,
      "total-borrowed": 0,
      "rate": 0.005,
      "hourly-rate": 5.723443223443223e-7,
      "liabilities": 0,
      "timestamp": 1717276458
    },
    "REXE-1": {
      "index": 1,
      "rexe_amount": 13,
      "rexe_supply": 1000,
      "total-borrowed": 0,
      "rate": 0.005,
      "hourly-rate": 5.723443223443223e-7,
      "liabilities": 0,
      "timestamp": 1717276458
    },
    "REXE-2": {
      "index": 1,
      "rexe_amount": 0,
      "rexe_supply": 1000,
      "total-borrowed": 0,
      "rate": 0.005,
      "hourly-rate": 5.723443223443223e-7,
      "liabilities": 0,
      "timestamp": 1717276458
    }
  },
  {
    "USDT-0": {
      "index": 1,
      "usdt_amount": 65.94,
      "usdt_supply": 1000,
      "total-borrowed": 0,
      "rate": 0.005,
      "hourly-rate": 5.723443223443223e-7,
      "liabilities": 0,
      "timestamp": 1717276468,
      "liability_charge": 0
    },
    "USDT-1": {
      "index": 1,
      "usdt_amount": 934.06,
      "usdt_supply": 1000,
      "total-borrowed": 0,
      "rate": 0.005,
      "hourly-rate": 5.723443223443223e-7,
      "liabilities": 0,
      "timestamp": 1717276468,
      "earningreate_charge": 0
    },
    "USDT-2": {
      "index": 1,
      "usdt_amount": 0,
      "usdt_supply": 1000,
      "total-borrowed": 0,
      "rate": 0.005,
      "hourly-rate": 5.723443223443223e-7,
      "liabilities": 0,
      "timestamp": 1717276468
    },
    "REXE-0": {
      "index": 1,
      "rexe_amount": 986,
      "rexe_supply": 1000,
      "total-borrowed": 0,
      "rate": 0.005,
      "hourly-rate": 5.723443223443223e-7,
      "liabilities": 0,
      "timestamp": 1717276468
    },
    "REXE-1": {
      "index": 1,
      "rexe_amount": 14,
      "rexe_supply": 1000,
      "total-borrowed": 0,
      "rate": 0.005,
      "hourly-rate": 5.723443223443223e-7,
      "liabilities": 0,
      "timestamp": 1717276468
    },
    "REXE-2": {
      "index": 1,
      "rexe_amount": 0,
      "rexe_supply": 1000,
      "total-borrowed": 0,
      "rate": 0.005,
      "hourly-rate": 5.723443223443223e-7,
      "liabilities": 0,
      "timestamp": 1717276468
    }
  },
  {
    "USDT-0": {
      "index": 1,
      "usdt_amount": 70.65,
      "usdt_supply": 1000,
      "total-borrowed": 0,
      "rate": 0.005,
      "hourly-rate": 5.723443223443223e-7,
      "liabilities": 0,
      "timestamp": 1717276478,
      "liability_charge": 0
    },
    "USDT-1": {
      "index": 1,
      "usdt_amount": 929.35,
      "usdt_supply": 1000,
      "total-borrowed": 0,
      "rate": 0.005,
      "hourly-rate": 5.723443223443223e-7,
      "liabilities": 0,
      "timestamp": 1717276478,
      "earningreate_charge": 0
    },
    "USDT-2": {
      "index": 1,
      "usdt_amount": 0,
      "usdt_supply": 1000,
      "total-borrowed": 0,
      "rate": 0.005,
      "hourly-rate": 5.723443223443223e-7,
      "liabilities": 0,
      "timestamp": 1717276478
    },
    "REXE-0": {
      "index": 1,
      "rexe_amount": 985,
      "rexe_supply": 1000,
      "total-borrowed": 0,
      "rate": 0.005,
      "hourly-rate": 5.723443223443223e-7,
      "liabilities": 0,
      "timestamp": 1717276478
    },
    "REXE-1": {
      "index": 1,
      "rexe_amount": 15,
      "rexe_supply": 1000,
      "total-borrowed": 0,
      "rate": 0.005,
      "hourly-rate": 5.723443223443223e-7,
      "liabilities": 0,
      "timestamp": 1717276478
    },
    "REXE-2": {
      "index": 1,
      "rexe_amount": 0,
      "rexe_supply": 1000,
      "total-borrowed": 0,
      "rate": 0.005,
      "hourly-rate": 5.723443223443223e-7,
      "liabilities": 0,
      "timestamp": 1717276478
    }
  },
  {
    "USDT-0": {
      "index": 1,
      "usdt_amount": 75.36,
      "usdt_supply": 1000,
      "total-borrowed": 0,
      "rate": 0.005,
      "hourly-rate": 5.723443223443223e-7,
      "liabilities": 0,
      "timestamp": 1717276488,
      "liability_charge": 0
    },
    "USDT-1": {
      "index": 1,
      "usdt_amount": 924.64,
      "usdt_supply": 1000,
      "total-borrowed": 0,
      "rate": 0.005,
      "hourly-rate": 5.723443223443223e-7,
      "liabilities": 0,
      "timestamp": 1717276488,
      "earningreate_charge": 0
    },
    "USDT-2": {
      "index": 1,
      "usdt_amount": 0,
      "usdt_supply": 1000,
      "total-borrowed": 0,
      "rate": 0.005,
      "hourly-rate": 5.723443223443223e-7,
      "liabilities": 0,
      "timestamp": 1717276488
    },
    "REXE-0": {
      "index": 1,
      "rexe_amount": 984,
      "rexe_supply": 1000,
      "total-borrowed": 0,
      "rate": 0.005,
      "hourly-rate": 5.723443223443223e-7,
      "liabilities": 0,
      "timestamp": 1717276488
    },
    "REXE-1": {
      "index": 1,
      "rexe_amount": 16,
      "rexe_supply": 1000,
      "total-borrowed": 0,
      "rate": 0.005,
      "hourly-rate": 5.723443223443223e-7,
      "liabilities": 0,
      "timestamp": 1717276488
    },
    "REXE-2": {
      "index": 1,
      "rexe_amount": 0,
      "rexe_supply": 1000,
      "total-borrowed": 0,
      "rate": 0.005,
      "hourly-rate": 5.723443223443223e-7,
      "liabilities": 0,
      "timestamp": 1717276488
    }
  },
  {
    "USDT-0": {
      "index": 1,
      "usdt_amount": 80.07,
      "usdt_supply": 1000,
      "total-borrowed": 0,
      "rate": 0.005,
      "hourly-rate": 5.723443223443223e-7,
      "liabilities": 0,
      "timestamp": 1717276498,
      "liability_charge": 0
    },
    "USDT-1": {
      "index": 1,
      "usdt_amount": 919.93,
      "usdt_supply": 1000,
      "total-borrowed": 0,
      "rate": 0.005,
      "hourly-rate": 5.723443223443223e-7,
      "liabilities": 0,
      "timestamp": 1717276498,
      "earningreate_charge": 0
    },
    "USDT-2": {
      "index": 1,
      "usdt_amount": 0,
      "usdt_supply": 1000,
      "total-borrowed": 0,
      "rate": 0.005,
      "hourly-rate": 5.723443223443223e-7,
      "liabilities": 0,
      "timestamp": 1717276498
    },
    "REXE-0": {
      "index": 1,
      "rexe_amount": 983,
      "rexe_supply": 1000,
      "total-borrowed": 0,
      "rate": 0.005,
      "hourly-rate": 5.723443223443223e-7,
      "liabilities": 0,
      "timestamp": 1717276498
    },
    "REXE-1": {
      "index": 1,
      "rexe_amount": 17,
      "rexe_supply": 1000,
      "total-borrowed": 0,
      "rate": 0.005,
      "hourly-rate": 5.723443223443223e-7,
      "liabilities": 0,
      "timestamp": 1717276498
    },
    "REXE-2": {
      "index": 1,
      "rexe_amount": 0,
      "rexe_supply": 1000,
      "total-borrowed": 0,
      "rate": 0.005,
      "hourly-rate": 5.723443223443223e-7,
      "liabilities": 0,
      "timestamp": 1717276498
    }
  },
  {
    "USDT-0": {
      "index": 1,
      "usdt_amount": 84.78,
      "usdt_supply": 1000,
      "total-borrowed": 0,
      "rate": 0.005,
      "hourly-rate": 5.723443223443223e-7,
      "liabilities": 0,
      "timestamp": 1717276508,
      "liability_charge": 0
    },
    "USDT-1": {
      "index": 1,
      "usdt_amount": 915.22,
      "usdt_supply": 1000,
      "total-borrowed": 0,
      "rate": 0.005,
      "hourly-rate": 5.723443223443223e-7,
      "liabilities": 0,
      "timestamp": 1717276508,
      "earningreate_charge": 0
    },
    "USDT-2": {
      "index": 1,
      "usdt_amount": 0,
      "usdt_supply": 1000,
      "total-borrowed": 0,
      "rate": 0.005,
      "hourly-rate": 5.723443223443223e-7,
      "liabilities": 0,
      "timestamp": 1717276508
    },
    "REXE-0": {
      "index": 1,
      "rexe_amount": 982,
      "rexe_supply": 1000,
      "total-borrowed": 0,
      "rate": 0.005,
      "hourly-rate": 5.723443223443223e-7,
      "liabilities": 0,
      "timestamp": 1717276508
    },
    "REXE-1": {
      "index": 1,
      "rexe_amount": 18,
      "rexe_supply": 1000,
      "total-borrowed": 0,
      "rate": 0.005,
      "hourly-rate": 5.723443223443223e-7,
      "liabilities": 0,
      "timestamp": 1717276508
    },
    "REXE-2": {
      "index": 1,
      "rexe_amount": 0,
      "rexe_supply": 1000,
      "total-borrowed": 0,
      "rate": 0.005,
      "hourly-rate": 5.723443223443223e-7,
      "liabilities": 0,
      "timestamp": 1717276508
    }
  },
  {
    "USDT-0": {
      "index": 1,
      "usdt_amount": 89.49,
      "usdt_supply": 1000,
      "total-borrowed": 0,
      "rate": 0.005,
      "hourly-rate": 5.723443223443223e-7,
      "liabilities": 0,
      "timestamp": 1717276518,
      "liability_charge": 0
    },
    "USDT-1": {
      "index": 1,
      "usdt_amount": 910.5100000000001,
      "usdt_supply": 1000,
      "total-borrowed": 0,
      "rate": 0.005,
      "hourly-rate": 5.723443223443223e-7,
      "liabilities": 0,
      "timestamp": 1717276518,
      "earningreate_charge": 0
    },
    "USDT-2": {
      "index": 1,
      "usdt_amount": 0,
      "usdt_supply": 1000,
      "total-borrowed": 0,
      "rate": 0.005,
      "hourly-rate": 5.723443223443223e-7,
      "liabilities": 0,
      "timestamp": 1717276518
    },
    "REXE-0": {
      "index": 1,
      "rexe_amount": 981,
      "rexe_supply": 1000,
      "total-borrowed": 0,
      "rate": 0.005,
      "hourly-rate": 5.723443223443223e-7,
      "liabilities": 0,
      "timestamp": 1717276518
    },
    "REXE-1": {
      "index": 1,
      "rexe_amount": 19,
      "rexe_supply": 1000,
      "total-borrowed": 0,
      "rate": 0.005,
      "hourly-rate": 5.723443223443223e-7,
      "liabilities": 0,
      "timestamp": 1717276518
    },
    "REXE-2": {
      "index": 1,
      "rexe_amount": 0,
      "rexe_supply": 1000,
      "total-borrowed": 0,
      "rate": 0.005,
      "hourly-rate": 5.723443223443223e-7,
      "liabilities": 0,
      "timestamp": 1717276518
    }
  },
  {
    "USDT-0": {
      "index": 1,
      "usdt_amount": 94.2,
      "usdt_supply": 1000,
      "total-borrowed": 0,
      "rate": 0.005,
      "hourly-rate": 5.723443223443223e-7,
      "liabilities": 0,
      "timestamp": 1717276528,
      "liability_charge": 0
    },
    "USDT-1": {
      "index": 1,
      "usdt_amount": 905.8,
      "usdt_supply": 1000,
      "total-borrowed": 0,
      "rate": 0.005,
      "hourly-rate": 5.723443223443223e-7,
      "liabilities": 0,
      "timestamp": 1717276528,
      "earningreate_charge": 0
    },
    "USDT-2": {
      "index": 1,
      "usdt_amount": 0,
      "usdt_supply": 1000,
      "total-borrowed": 0,
      "rate": 0.005,
      "hourly-rate": 5.723443223443223e-7,
      "liabilities": 0,
      "timestamp": 1717276528
    },
    "REXE-0": {
      "index": 1,
      "rexe_amount": 980,
      "rexe_supply": 1000,
      "total-borrowed": 0,
      "rate": 0.005,
      "hourly-rate": 5.723443223443223e-7,
      "liabilities": 0,
      "timestamp": 1717276528
    },
    "REXE-1": {
      "index": 1,
      "rexe_amount": 20,
      "rexe_supply": 1000,
      "total-borrowed": 0,
      "rate": 0.005,
      "hourly-rate": 5.723443223443223e-7,
      "liabilities": 0,
      "timestamp": 1717276528
    },
    "REXE-2": {
      "index": 1,
      "rexe_amount": 0,
      "rexe_supply": 1000,
      "total-borrowed": 0,
      "rate": 0.005,
      "hourly-rate": 5.723443223443223e-7,
      "liabilities": 0,
      "timestamp": 1717276528
    }
  },
  {
    "USDT-0": {
      "index": 1,
      "usdt_amount": 98.91,
      "usdt_supply": 1000,
      "total-borrowed": 0,
      "rate": 0.005,
      "hourly-rate": 5.723443223443223e-7,
      "liabilities": 0,
      "timestamp": 1717276538,
      "liability_charge": 0
    },
    "USDT-1": {
      "index": 1,
      "usdt_amount": 901.0899999999999,
      "usdt_supply": 1000,
      "total-borrowed": 0,
      "rate": 0.005,
      "hourly-rate": 5.723443223443223e-7,
      "liabilities": 0,
      "timestamp": 1717276538,
      "earningreate_charge": 0
    },
    "USDT-2": {
      "index": 1,
      "usdt_amount": 0,
      "usdt_supply": 1000,
      "total-borrowed": 0,
      "rate": 0.005,
      "hourly-rate": 5.723443223443223e-7,
      "liabilities": 0,
      "timestamp": 1717276538
    },
    "REXE-0": {
      "index": 1,
      "rexe_amount": 979,
      "rexe_supply": 1000,
      "total-borrowed": 0,
      "rate": 0.005,
      "hourly-rate": 5.723443223443223e-7,
      "liabilities": 0,
      "timestamp": 1717276538
    },
    "REXE-1": {
      "index": 1,
      "rexe_amount": 21,
      "rexe_supply": 1000,
      "total-borrowed": 0,
      "rate": 0.005,
      "hourly-rate": 5.723443223443223e-7,
      "liabilities": 0,
      "timestamp": 1717276538
    },
    "REXE-2": {
      "index": 1,
      "rexe_amount": 0,
      "rexe_supply": 1000,
      "total-borrowed": 0,
      "rate": 0.005,
      "hourly-rate": 5.723443223443223e-7,
      "liabilities": 0,
      "timestamp": 1717276538
    }
  },
  {
    "USDT-0": {
      "index": 1,
      "usdt_amount": 103.62,
      "usdt_supply": 1000,
      "total-borrowed": 0,
      "rate": 0.005,
      "hourly-rate": 5.723443223443223e-7,
      "liabilities": 0,
      "timestamp": 1717276548,
      "liability_charge": 0
    },
    "USDT-1": {
      "index": 1,
      "usdt_amount": 896.38,
      "usdt_supply": 1000,
      "total-borrowed": 0,
      "rate": 0.005,
      "hourly-rate": 5.723443223443223e-7,
      "liabilities": 0,
      "timestamp": 1717276548,
      "earningreate_charge": 0
    },
    "USDT-2": {
      "index": 1,
      "usdt_amount": 0,
      "usdt_supply": 1000,
      "total-borrowed": 0,
      "rate": 0.005,
      "hourly-rate": 5.723443223443223e-7,
      "liabilities": 0,
      "timestamp": 1717276548
    },
    "REXE-0": {
      "index": 1,
      "rexe_amount": 978,
      "rexe_supply": 1000,
      "total-borrowed": 0,
      "rate": 0.005,
      "hourly-rate": 5.723443223443223e-7,
      "liabilities": 0,
      "timestamp": 1717276548
    },
    "REXE-1": {
      "index": 1,
      "rexe_amount": 22,
      "rexe_supply": 1000,
      "total-borrowed": 0,
      "rate": 0.005,
      "hourly-rate": 5.723443223443223e-7,
      "liabilities": 0,
      "timestamp": 1717276548
    },
    "REXE-2": {
      "index": 1,
      "rexe_amount": 0,
      "rexe_supply": 1000,
      "total-borrowed": 0,
      "rate": 0.005,
      "hourly-rate": 5.723443223443223e-7,
      "liabilities": 0,
      "timestamp": 1717276548
    }
  },
  {
    "USDT-0": {
      "index": 1,
      "usdt_amount": 108.33,
      "usdt_supply": 1000,
      "total-borrowed": 0,
      "rate": 0.005,
      "hourly-rate": 5.723443223443223e-7,
      "liabilities": 0,
      "timestamp": 1717276558,
      "liability_charge": 0
    },
    "USDT-1": {
      "index": 1,
      "usdt_amount": 891.6700000000001,
      "usdt_supply": 1000,
      "total-borrowed": 0,
      "rate": 0.005,
      "hourly-rate": 5.723443223443223e-7,
      "liabilities": 0,
      "timestamp": 1717276558,
      "earningreate_charge": 0
    },
    "USDT-2": {
      "index": 1,
      "usdt_amount": 0,
      "usdt_supply": 1000,
      "total-borrowed": 0,
      "rate": 0.005,
      "hourly-rate": 5.723443223443223e-7,
      "liabilities": 0,
      "timestamp": 1717276558
    },
    "REXE-0": {
      "index": 1,
      "rexe_amount": 977,
      "rexe_supply": 1000,
      "total-borrowed": 0,
      "rate": 0.005,
      "hourly-rate": 5.723443223443223e-7,
      "liabilities": 0,
      "timestamp": 1717276558
    },
    "REXE-1": {
      "index": 1,
      "rexe_amount": 23,
      "rexe_supply": 1000,
      "total-borrowed": 0,
      "rate": 0.005,
      "hourly-rate": 5.723443223443223e-7,
      "liabilities": 0,
      "timestamp": 1717276558
    },
    "REXE-2": {
      "index": 1,
      "rexe_amount": 0,
      "rexe_supply": 1000,
      "total-borrowed": 0,
      "rate": 0.005,
      "hourly-rate": 5.723443223443223e-7,
      "liabilities": 0,
      "timestamp": 1717276558
    }
  },
  {
    "USDT-0": {
      "index": 1,
      "usdt_amount": 113.04,
      "usdt_supply": 1000,
      "total-borrowed": 0,
      "rate": 0.005,
      "hourly-rate": 5.723443223443223e-7,
      "liabilities": 0,
      "timestamp": 1717276568,
      "liability_charge": 0
    },
    "USDT-1": {
      "index": 1,
      "usdt_amount": 886.96,
      "usdt_supply": 1000,
      "total-borrowed": 0,
      "rate": 0.005,
      "hourly-rate": 5.723443223443223e-7,
      "liabilities": 0,
      "timestamp": 1717276568,
      "earningreate_charge": 0
    },
    "USDT-2": {
      "index": 1,
      "usdt_amount": 0,
      "usdt_supply": 1000,
      "total-borrowed": 0,
      "rate": 0.005,
      "hourly-rate": 5.723443223443223e-7,
      "liabilities": 0,
      "timestamp": 1717276568
    },
    "REXE-0": {
      "index": 1,
      "rexe_amount": 976,
      "rexe_supply": 1000,
      "total-borrowed": 0,
      "rate": 0.005,
      "hourly-rate": 5.723443223443223e-7,
      "liabilities": 0,
      "timestamp": 1717276568
    },
    "REXE-1": {
      "index": 1,
      "rexe_amount": 24,
      "rexe_supply": 1000,
      "total-borrowed": 0,
      "rate": 0.005,
      "hourly-rate": 5.723443223443223e-7,
      "liabilities": 0,
      "timestamp": 1717276568
    },
    "REXE-2": {
      "index": 1,
      "rexe_amount": 0,
      "rexe_supply": 1000,
      "total-borrowed": 0,
      "rate": 0.005,
      "hourly-rate": 5.723443223443223e-7,
      "liabilities": 0,
      "timestamp": 1717276568
    }
  },
  {
    "USDT-0": {
      "index": 1,
      "usdt_amount": 117.75,
      "usdt_supply": 1000,
      "total-borrowed": 0,
      "rate": 0.005,
      "hourly-rate": 5.723443223443223e-7,
      "liabilities": 0,
      "timestamp": 1717276578,
      "liability_charge": 0
    },
    "USDT-1": {
      "index": 1,
      "usdt_amount": 882.2499999999999,
      "usdt_supply": 1000,
      "total-borrowed": 0,
      "rate": 0.005,
      "hourly-rate": 5.723443223443223e-7,
      "liabilities": 0,
      "timestamp": 1717276578,
      "earningreate_charge": 0
    },
    "USDT-2": {
      "index": 1,
      "usdt_amount": 0,
      "usdt_supply": 1000,
      "total-borrowed": 0,
      "rate": 0.005,
      "hourly-rate": 5.723443223443223e-7,
      "liabilities": 0,
      "timestamp": 1717276578
    },
    "REXE-0": {
      "index": 1,
      "rexe_amount": 975,
      "rexe_supply": 1000,
      "total-borrowed": 0,
      "rate": 0.005,
      "hourly-rate": 5.723443223443223e-7,
      "liabilities": 0,
      "timestamp": 1717276578
    },
    "REXE-1": {
      "index": 1,
      "rexe_amount": 25,
      "rexe_supply": 1000,
      "total-borrowed": 0,
      "rate": 0.005,
      "hourly-rate": 5.723443223443223e-7,
      "liabilities": 0,
      "timestamp": 1717276578
    },
    "REXE-2": {
      "index": 1,
      "rexe_amount": 0,
      "rexe_supply": 1000,
      "total-borrowed": 0,
      "rate": 0.005,
      "hourly-rate": 5.723443223443223e-7,
      "liabilities": 0,
      "timestamp": 1717276578
    }
  },
  {
    "USDT-0": {
      "index": 1,
      "usdt_amount": 122.46,
      "usdt_supply": 1000,
      "total-borrowed": 0,
      "rate": 0.005,
      "hourly-rate": 5.723443223443223e-7,
      "liabilities": 0,
      "timestamp": 1717276588,
      "liability_charge": 0
    },
    "USDT-1": {
      "index": 1,
      "usdt_amount": 877.54,
      "usdt_supply": 1000,
      "total-borrowed": 0,
      "rate": 0.005,
      "hourly-rate": 5.723443223443223e-7,
      "liabilities": 0,
      "timestamp": 1717276588,
      "earningreate_charge": 0
    },
    "USDT-2": {
      "index": 1,
      "usdt_amount": 0,
      "usdt_supply": 1000,
      "total-borrowed": 0,
      "rate": 0.005,
      "hourly-rate": 5.723443223443223e-7,
      "liabilities": 0,
      "timestamp": 1717276588
    },
    "REXE-0": {
      "index": 1,
      "rexe_amount": 974,
      "rexe_supply": 1000,
      "total-borrowed": 0,
      "rate": 0.005,
      "hourly-rate": 5.723443223443223e-7,
      "liabilities": 0,
      "timestamp": 1717276588
    },
    "REXE-1": {
      "index": 1,
      "rexe_amount": 26,
      "rexe_supply": 1000,
      "total-borrowed": 0,
      "rate": 0.005,
      "hourly-rate": 5.723443223443223e-7,
      "liabilities": 0,
      "timestamp": 1717276588
    },
    "REXE-2": {
      "index": 1,
      "rexe_amount": 0,
      "rexe_supply": 1000,
      "total-borrowed": 0,
      "rate": 0.005,
      "hourly-rate": 5.723443223443223e-7,
      "liabilities": 0,
      "timestamp": 1717276588
    }
  },
  {
    "USDT-0": {
      "index": 1,
      "usdt_amount": 127.17,
      "usdt_supply": 1000,
      "total-borrowed": 0,
      "rate": 0.005,
      "hourly-rate": 5.723443223443223e-7,
      "liabilities": 0,
      "timestamp": 1717276598,
      "liability_charge": 0
    },
    "USDT-1": {
      "index": 1,
      "usdt_amount": 872.83,
      "usdt_supply": 1000,
      "total-borrowed": 0,
      "rate": 0.005,
      "hourly-rate": 5.723443223443223e-7,
      "liabilities": 0,
      "timestamp": 1717276598,
      "earningreate_charge": 0
    },
    "USDT-2": {
      "index": 1,
      "usdt_amount": 0,
      "usdt_supply": 1000,
      "total-borrowed": 0,
      "rate": 0.005,
      "hourly-rate": 5.723443223443223e-7,
      "liabilities": 0,
      "timestamp": 1717276598
    },
    "REXE-0": {
      "index": 1,
      "rexe_amount": 973,
      "rexe_supply": 1000,
      "total-borrowed": 0,
      "rate": 0.005,
      "hourly-rate": 5.723443223443223e-7,
      "liabilities": 0,
      "timestamp": 1717276598
    },
    "REXE-1": {
      "index": 1,
      "rexe_amount": 27,
      "rexe_supply": 1000,
      "total-borrowed": 0,
      "rate": 0.005,
      "hourly-rate": 5.723443223443223e-7,
      "liabilities": 0,
      "timestamp": 1717276598
    },
    "REXE-2": {
      "index": 1,
      "rexe_amount": 0,
      "rexe_supply": 1000,
      "total-borrowed": 0,
      "rate": 0.005,
      "hourly-rate": 5.723443223443223e-7,
      "liabilities": 0,
      "timestamp": 1717276598
    }
  },
  {
    "USDT-0": {
      "index": 1,
      "usdt_amount": 131.88,
      "usdt_supply": 1000,
      "total-borrowed": 0,
      "rate": 0.005,
      "hourly-rate": 5.723443223443223e-7,
      "liabilities": 0,
      "timestamp": 1717276608,
      "liability_charge": 0
    },
    "USDT-1": {
      "index": 1,
      "usdt_amount": 868.12,
      "usdt_supply": 1000,
      "total-borrowed": 0,
      "rate": 0.005,
      "hourly-rate": 5.723443223443223e-7,
      "liabilities": 0,
      "timestamp": 1717276608,
      "earningreate_charge": 0
    },
    "USDT-2": {
      "index": 1,
      "usdt_amount": 0,
      "usdt_supply": 1000,
      "total-borrowed": 0,
      "rate": 0.005,
      "hourly-rate": 5.723443223443223e-7,
      "liabilities": 0,
      "timestamp": 1717276608
    },
    "REXE-0": {
      "index": 1,
      "rexe_amount": 972,
      "rexe_supply": 1000,
      "total-borrowed": 0,
      "rate": 0.005,
      "hourly-rate": 5.723443223443223e-7,
      "liabilities": 0,
      "timestamp": 1717276608
    },
    "REXE-1": {
      "index": 1,
      "rexe_amount": 28,
      "rexe_supply": 1000,
      "total-borrowed": 0,
      "rate": 0.005,
      "hourly-rate": 5.723443223443223e-7,
      "liabilities": 0,
      "timestamp": 1717276608
    },
    "REXE-2": {
      "index": 1,
      "rexe_amount": 0,
      "rexe_supply": 1000,
      "total-borrowed": 0,
      "rate": 0.005,
      "hourly-rate": 5.723443223443223e-7,
      "liabilities": 0,
      "timestamp": 1717276608
    }
  },
  {
    "USDT-0": {
      "index": 1,
      "usdt_amount": 136.59,
      "usdt_supply": 1000,
      "total-borrowed": 0,
      "rate": 0.005,
      "hourly-rate": 5.723443223443223e-7,
      "liabilities": 0,
      "timestamp": 1717276618,
      "liability_charge": 0
    },
    "USDT-1": {
      "index": 1,
      "usdt_amount": 863.41,
      "usdt_supply": 1000,
      "total-borrowed": 0,
      "rate": 0.005,
      "hourly-rate": 5.723443223443223e-7,
      "liabilities": 0,
      "timestamp": 1717276618,
      "earningreate_charge": 0
    },
    "USDT-2": {
      "index": 1,
      "usdt_amount": 0,
      "usdt_supply": 1000,
      "total-borrowed": 0,
      "rate": 0.005,
      "hourly-rate": 5.723443223443223e-7,
      "liabilities": 0,
      "timestamp": 1717276618
    },
    "REXE-0": {
      "index": 1,
      "rexe_amount": 971,
      "rexe_supply": 1000,
      "total-borrowed": 0,
      "rate": 0.005,
      "hourly-rate": 5.723443223443223e-7,
      "liabilities": 0,
      "timestamp": 1717276618
    },
    "REXE-1": {
      "index": 1,
      "rexe_amount": 29,
      "rexe_supply": 1000,
      "total-borrowed": 0,
      "rate": 0.005,
      "hourly-rate": 5.723443223443223e-7,
      "liabilities": 0,
      "timestamp": 1717276618
    },
    "REXE-2": {
      "index": 1,
      "rexe_amount": 0,
      "rexe_supply": 1000,
      "total-borrowed": 0,
      "rate": 0.005,
      "hourly-rate": 5.723443223443223e-7,
      "liabilities": 0,
      "timestamp": 1717276618
    }
  },
  {
    "USDT-0": {
      "index": 1,
      "usdt_amount": 141.3,
      "usdt_supply": 1000,
      "total-borrowed": 0,
      "rate": 0.005,
      "hourly-rate": 5.723443223443223e-7,
      "liabilities": 0,
      "timestamp": 1717276628,
      "liability_charge": 0
    },
    "USDT-1": {
      "index": 1,
      "usdt_amount": 858.7,
      "usdt_supply": 1000,
      "total-borrowed": 0,
      "rate": 0.005,
      "hourly-rate": 5.723443223443223e-7,
      "liabilities": 0,
      "timestamp": 1717276628,
      "earningreate_charge": 0
    },
    "USDT-2": {
      "index": 1,
      "usdt_amount": 0,
      "usdt_supply": 1000,
      "total-borrowed": 0,
      "rate": 0.005,
      "hourly-rate": 5.723443223443223e-7,
      "liabilities": 0,
      "timestamp": 1717276628
    },
    "REXE-0": {
      "index": 1,
      "rexe_amount": 970,
      "rexe_supply": 1000,
      "total-borrowed": 0,
      "rate": 0.005,
      "hourly-rate": 5.723443223443223e-7,
      "liabilities": 0,
      "timestamp": 1717276628
    },
    "REXE-1": {
      "index": 1,
      "rexe_amount": 30,
      "rexe_supply": 1000,
      "total-borrowed": 0,
      "rate": 0.005,
      "hourly-rate": 5.723443223443223e-7,
      "liabilities": 0,
      "timestamp": 1717276628
    },
    "REXE-2": {
      "index": 1,
      "rexe_amount": 0,
      "rexe_supply": 1000,
      "total-borrowed": 0,
      "rate": 0.005,
      "hourly-rate": 5.723443223443223e-7,
      "liabilities": 0,
      "timestamp": 1717276628
    }
  },
  {
    "USDT-0": {
      "index": 1,
      "usdt_amount": 146.01,
      "usdt_supply": 1000,
      "total-borrowed": 0,
      "rate": 0.005,
      "hourly-rate": 5.723443223443223e-7,
      "liabilities": 0,
      "timestamp": 1717276638,
      "liability_charge": 0
    },
    "USDT-1": {
      "index": 1,
      "usdt_amount": 853.99,
      "usdt_supply": 1000,
      "total-borrowed": 0,
      "rate": 0.005,
      "hourly-rate": 5.723443223443223e-7,
      "liabilities": 0,
      "timestamp": 1717276638,
      "earningreate_charge": 0
    },
    "USDT-2": {
      "index": 1,
      "usdt_amount": 0,
      "usdt_supply": 1000,
      "total-borrowed": 0,
      "rate": 0.005,
      "hourly-rate": 5.723443223443223e-7,
      "liabilities": 0,
      "timestamp": 1717276638
    },
    "REXE-0": {
      "index": 1,
      "rexe_amount": 969,
      "rexe_supply": 1000,
      "total-borrowed": 0,
      "rate": 0.005,
      "hourly-rate": 5.723443223443223e-7,
      "liabilities": 0,
      "timestamp": 1717276638
    },
    "REXE-1": {
      "index": 1,
      "rexe_amount": 31,
      "rexe_supply": 1000,
      "total-borrowed": 0,
      "rate": 0.005,
      "hourly-rate": 5.723443223443223e-7,
      "liabilities": 0,
      "timestamp": 1717276638
    },
    "REXE-2": {
      "index": 1,
      "rexe_amount": 0,
      "rexe_supply": 1000,
      "total-borrowed": 0,
      "rate": 0.005,
      "hourly-rate": 5.723443223443223e-7,
      "liabilities": 0,
      "timestamp": 1717276638
    }
  },
  {
    "USDT-0": {
      "index": 1,
      "usdt_amount": 150.72,
      "usdt_supply": 1000,
      "total-borrowed": 0,
      "rate": 0.005,
      "hourly-rate": 5.723443223443223e-7,
      "liabilities": 0,
      "timestamp": 1717276648,
      "liability_charge": 0
    },
    "USDT-1": {
      "index": 1,
      "usdt_amount": 849.28,
      "usdt_supply": 1000,
      "total-borrowed": 0,
      "rate": 0.005,
      "hourly-rate": 5.723443223443223e-7,
      "liabilities": 0,
      "timestamp": 1717276648,
      "earningreate_charge": 0
    },
    "USDT-2": {
      "index": 1,
      "usdt_amount": 0,
      "usdt_supply": 1000,
      "total-borrowed": 0,
      "rate": 0.005,
      "hourly-rate": 5.723443223443223e-7,
      "liabilities": 0,
      "timestamp": 1717276648
    },
    "REXE-0": {
      "index": 1,
      "rexe_amount": 968,
      "rexe_supply": 1000,
      "total-borrowed": 0,
      "rate": 0.005,
      "hourly-rate": 5.723443223443223e-7,
      "liabilities": 0,
      "timestamp": 1717276648
    },
    "REXE-1": {
      "index": 1,
      "rexe_amount": 32,
      "rexe_supply": 1000,
      "total-borrowed": 0,
      "rate": 0.005,
      "hourly-rate": 5.723443223443223e-7,
      "liabilities": 0,
      "timestamp": 1717276648
    },
    "REXE-2": {
      "index": 1,
      "rexe_amount": 0,
      "rexe_supply": 1000,
      "total-borrowed": 0,
      "rate": 0.005,
      "hourly-rate": 5.723443223443223e-7,
      "liabilities": 0,
      "timestamp": 1717276648
    }
  },
  {
    "USDT-0": {
      "index": 1,
      "usdt_amount": 155.43,
      "usdt_supply": 1000,
      "total-borrowed": 0,
      "rate": 0.005,
      "hourly-rate": 5.723443223443223e-7,
      "liabilities": 0,
      "timestamp": 1717276658,
      "liability_charge": 0
    },
    "USDT-1": {
      "index": 1,
      "usdt_amount": 844.5699999999999,
      "usdt_supply": 1000,
      "total-borrowed": 0,
      "rate": 0.005,
      "hourly-rate": 5.723443223443223e-7,
      "liabilities": 0,
      "timestamp": 1717276658,
      "earningreate_charge": 0
    },
    "USDT-2": {
      "index": 1,
      "usdt_amount": 0,
      "usdt_supply": 1000,
      "total-borrowed": 0,
      "rate": 0.005,
      "hourly-rate": 5.723443223443223e-7,
      "liabilities": 0,
      "timestamp": 1717276658
    },
    "REXE-0": {
      "index": 1,
      "rexe_amount": 967,
      "rexe_supply": 1000,
      "total-borrowed": 0,
      "rate": 0.005,
      "hourly-rate": 5.723443223443223e-7,
      "liabilities": 0,
      "timestamp": 1717276658
    },
    "REXE-1": {
      "index": 1,
      "rexe_amount": 33,
      "rexe_supply": 1000,
      "total-borrowed": 0,
      "rate": 0.005,
      "hourly-rate": 5.723443223443223e-7,
      "liabilities": 0,
      "timestamp": 1717276658
    },
    "REXE-2": {
      "index": 1,
      "rexe_amount": 0,
      "rexe_supply": 1000,
      "total-borrowed": 0,
      "rate": 0.005,
      "hourly-rate": 5.723443223443223e-7,
      "liabilities": 0,
      "timestamp": 1717276658
    }
  },
  {
    "USDT-0": {
      "index": 1,
      "usdt_amount": 160.14,
      "usdt_supply": 1000,
      "total-borrowed": 0,
      "rate": 0.005,
      "hourly-rate": 5.723443223443223e-7,
      "liabilities": 0,
      "timestamp": 1717276668,
      "liability_charge": 0
    },
    "USDT-1": {
      "index": 1,
      "usdt_amount": 839.86,
      "usdt_supply": 1000,
      "total-borrowed": 0,
      "rate": 0.005,
      "hourly-rate": 5.723443223443223e-7,
      "liabilities": 0,
      "timestamp": 1717276668,
      "earningreate_charge": 0
    },
    "USDT-2": {
      "index": 1,
      "usdt_amount": 0,
      "usdt_supply": 1000,
      "total-borrowed": 0,
      "rate": 0.005,
      "hourly-rate": 5.723443223443223e-7,
      "liabilities": 0,
      "timestamp": 1717276668
    },
    "REXE-0": {
      "index": 1,
      "rexe_amount": 966,
      "rexe_supply": 1000,
      "total-borrowed": 0,
      "rate": 0.005,
      "hourly-rate": 5.723443223443223e-7,
      "liabilities": 0,
      "timestamp": 1717276668
    },
    "REXE-1": {
      "index": 1,
      "rexe_amount": 34,
      "rexe_supply": 1000,
      "total-borrowed": 0,
      "rate": 0.005,
      "hourly-rate": 5.723443223443223e-7,
      "liabilities": 0,
      "timestamp": 1717276668
    },
    "REXE-2": {
      "index": 1,
      "rexe_amount": 0,
      "rexe_supply": 1000,
      "total-borrowed": 0,
      "rate": 0.005,
      "hourly-rate": 5.723443223443223e-7,
      "liabilities": 0,
      "timestamp": 1717276668
    }
  },
  {
    "USDT-0": {
      "index": 1,
      "usdt_amount": 164.85,
      "usdt_supply": 1000,
      "total-borrowed": 0,
      "rate": 0.005,
      "hourly-rate": 5.723443223443223e-7,
      "liabilities": 0,
      "timestamp": 1717276678,
      "liability_charge": 0
    },
    "USDT-1": {
      "index": 1,
      "usdt_amount": 835.1500000000001,
      "usdt_supply": 1000,
      "total-borrowed": 0,
      "rate": 0.005,
      "hourly-rate": 5.723443223443223e-7,
      "liabilities": 0,
      "timestamp": 1717276678,
      "earningreate_charge": 0
    },
    "USDT-2": {
      "index": 1,
      "usdt_amount": 0,
      "usdt_supply": 1000,
      "total-borrowed": 0,
      "rate": 0.005,
      "hourly-rate": 5.723443223443223e-7,
      "liabilities": 0,
      "timestamp": 1717276678
    },
    "REXE-0": {
      "index": 1,
      "rexe_amount": 965,
      "rexe_supply": 1000,
      "total-borrowed": 0,
      "rate": 0.005,
      "hourly-rate": 5.723443223443223e-7,
      "liabilities": 0,
      "timestamp": 1717276678
    },
    "REXE-1": {
      "index": 1,
      "rexe_amount": 35,
      "rexe_supply": 1000,
      "total-borrowed": 0,
      "rate": 0.005,
      "hourly-rate": 5.723443223443223e-7,
      "liabilities": 0,
      "timestamp": 1717276678
    },
    "REXE-2": {
      "index": 1,
      "rexe_amount": 0,
      "rexe_supply": 1000,
      "total-borrowed": 0,
      "rate": 0.005,
      "hourly-rate": 5.723443223443223e-7,
      "liabilities": 0,
      "timestamp": 1717276678
    }
  },
  {
    "USDT-0": {
      "index": 1,
      "usdt_amount": 169.56,
      "usdt_supply": 1000,
      "total-borrowed": 0,
      "rate": 0.005,
      "hourly-rate": 5.723443223443223e-7,
      "liabilities": 0,
      "timestamp": 1717276688,
      "liability_charge": 0
    },
    "USDT-1": {
      "index": 1,
      "usdt_amount": 830.44,
      "usdt_supply": 1000,
      "total-borrowed": 0,
      "rate": 0.005,
      "hourly-rate": 5.723443223443223e-7,
      "liabilities": 0,
      "timestamp": 1717276688,
      "earningreate_charge": 0
    },
    "USDT-2": {
      "index": 1,
      "usdt_amount": 0,
      "usdt_supply": 1000,
      "total-borrowed": 0,
      "rate": 0.005,
      "hourly-rate": 5.723443223443223e-7,
      "liabilities": 0,
      "timestamp": 1717276688
    },
    "REXE-0": {
      "index": 1,
      "rexe_amount": 964,
      "rexe_supply": 1000,
      "total-borrowed": 0,
      "rate": 0.005,
      "hourly-rate": 5.723443223443223e-7,
      "liabilities": 0,
      "timestamp": 1717276688
    },
    "REXE-1": {
      "index": 1,
      "rexe_amount": 36,
      "rexe_supply": 1000,
      "total-borrowed": 0,
      "rate": 0.005,
      "hourly-rate": 5.723443223443223e-7,
      "liabilities": 0,
      "timestamp": 1717276688
    },
    "REXE-2": {
      "index": 1,
      "rexe_amount": 0,
      "rexe_supply": 1000,
      "total-borrowed": 0,
      "rate": 0.005,
      "hourly-rate": 5.723443223443223e-7,
      "liabilities": 0,
      "timestamp": 1717276688
    }
  },
  {
    "USDT-0": {
      "index": 1,
      "usdt_amount": 174.27,
      "usdt_supply": 1000,
      "total-borrowed": 0,
      "rate": 0.005,
      "hourly-rate": 5.723443223443223e-7,
      "liabilities": 0,
      "timestamp": 1717276698,
      "liability_charge": 0
    },
    "USDT-1": {
      "index": 1,
      "usdt_amount": 825.7299999999999,
      "usdt_supply": 1000,
      "total-borrowed": 0,
      "rate": 0.005,
      "hourly-rate": 5.723443223443223e-7,
      "liabilities": 0,
      "timestamp": 1717276698,
      "earningreate_charge": 0
    },
    "USDT-2": {
      "index": 1,
      "usdt_amount": 0,
      "usdt_supply": 1000,
      "total-borrowed": 0,
      "rate": 0.005,
      "hourly-rate": 5.723443223443223e-7,
      "liabilities": 0,
      "timestamp": 1717276698
    },
    "REXE-0": {
      "index": 1,
      "rexe_amount": 963,
      "rexe_supply": 1000,
      "total-borrowed": 0,
      "rate": 0.005,
      "hourly-rate": 5.723443223443223e-7,
      "liabilities": 0,
      "timestamp": 1717276698
    },
    "REXE-1": {
      "index": 1,
      "rexe_amount": 37,
      "rexe_supply": 1000,
      "total-borrowed": 0,
      "rate": 0.005,
      "hourly-rate": 5.723443223443223e-7,
      "liabilities": 0,
      "timestamp": 1717276698
    },
    "REXE-2": {
      "index": 1,
      "rexe_amount": 0,
      "rexe_supply": 1000,
      "total-borrowed": 0,
      "rate": 0.005,
      "hourly-rate": 5.723443223443223e-7,
      "liabilities": 0,
      "timestamp": 1717276698
    }
  },
  {
    "USDT-0": {
      "index": 1,
      "usdt_amount": 178.98,
      "usdt_supply": 1000,
      "total-borrowed": 0,
      "rate": 0.005,
      "hourly-rate": 5.723443223443223e-7,
      "liabilities": 0,
      "timestamp": 1717276708,
      "liability_charge": 0
    },
    "USDT-1": {
      "index": 1,
      "usdt_amount": 821.02,
      "usdt_supply": 1000,
      "total-borrowed": 0,
      "rate": 0.005,
      "hourly-rate": 5.723443223443223e-7,
      "liabilities": 0,
      "timestamp": 1717276708,
      "earningreate_charge": 0
    },
    "USDT-2": {
      "index": 1,
      "usdt_amount": 0,
      "usdt_supply": 1000,
      "total-borrowed": 0,
      "rate": 0.005,
      "hourly-rate": 5.723443223443223e-7,
      "liabilities": 0,
      "timestamp": 1717276708
    },
    "REXE-0": {
      "index": 1,
      "rexe_amount": 962,
      "rexe_supply": 1000,
      "total-borrowed": 0,
      "rate": 0.005,
      "hourly-rate": 5.723443223443223e-7,
      "liabilities": 0,
      "timestamp": 1717276708
    },
    "REXE-1": {
      "index": 1,
      "rexe_amount": 38,
      "rexe_supply": 1000,
      "total-borrowed": 0,
      "rate": 0.005,
      "hourly-rate": 5.723443223443223e-7,
      "liabilities": 0,
      "timestamp": 1717276708
    },
    "REXE-2": {
      "index": 1,
      "rexe_amount": 0,
      "rexe_supply": 1000,
      "total-borrowed": 0,
      "rate": 0.005,
      "hourly-rate": 5.723443223443223e-7,
      "liabilities": 0,
      "timestamp": 1717276708
    }
  },
  {
    "USDT-0": {
      "index": 1,
      "usdt_amount": 183.69,
      "usdt_supply": 1000,
      "total-borrowed": 0,
      "rate": 0.005,
      "hourly-rate": 5.723443223443223e-7,
      "liabilities": 0,
      "timestamp": 1717276718,
      "liability_charge": 0
    },
    "USDT-1": {
      "index": 1,
      "usdt_amount": 816.3100000000001,
      "usdt_supply": 1000,
      "total-borrowed": 0,
      "rate": 0.005,
      "hourly-rate": 5.723443223443223e-7,
      "liabilities": 0,
      "timestamp": 1717276718,
      "earningreate_charge": 0
    },
    "USDT-2": {
      "index": 1,
      "usdt_amount": 0,
      "usdt_supply": 1000,
      "total-borrowed": 0,
      "rate": 0.005,
      "hourly-rate": 5.723443223443223e-7,
      "liabilities": 0,
      "timestamp": 1717276718
    },
    "REXE-0": {
      "index": 1,
      "rexe_amount": 961,
      "rexe_supply": 1000,
      "total-borrowed": 0,
      "rate": 0.005,
      "hourly-rate": 5.723443223443223e-7,
      "liabilities": 0,
      "timestamp": 1717276718
    },
    "REXE-1": {
      "index": 1,
      "rexe_amount": 39,
      "rexe_supply": 1000,
      "total-borrowed": 0,
      "rate": 0.005,
      "hourly-rate": 5.723443223443223e-7,
      "liabilities": 0,
      "timestamp": 1717276718
    },
    "REXE-2": {
      "index": 1,
      "rexe_amount": 0,
      "rexe_supply": 1000,
      "total-borrowed": 0,
      "rate": 0.005,
      "hourly-rate": 5.723443223443223e-7,
      "liabilities": 0,
      "timestamp": 1717276718
    }
  },
  {
    "USDT-0": {
      "index": 1,
      "usdt_amount": 188.4,
      "usdt_supply": 1000,
      "total-borrowed": 0,
      "rate": 0.005,
      "hourly-rate": 5.723443223443223e-7,
      "liabilities": 0,
      "timestamp": 1717276728,
      "liability_charge": 0
    },
    "USDT-1": {
      "index": 1,
      "usdt_amount": 811.6,
      "usdt_supply": 1000,
      "total-borrowed": 0,
      "rate": 0.005,
      "hourly-rate": 5.723443223443223e-7,
      "liabilities": 0,
      "timestamp": 1717276728,
      "earningreate_charge": 0
    },
    "USDT-2": {
      "index": 1,
      "usdt_amount": 0,
      "usdt_supply": 1000,
      "total-borrowed": 0,
      "rate": 0.005,
      "hourly-rate": 5.723443223443223e-7,
      "liabilities": 0,
      "timestamp": 1717276728
    },
    "REXE-0": {
      "index": 1,
      "rexe_amount": 960,
      "rexe_supply": 1000,
      "total-borrowed": 0,
      "rate": 0.005,
      "hourly-rate": 5.723443223443223e-7,
      "liabilities": 0,
      "timestamp": 1717276728
    },
    "REXE-1": {
      "index": 1,
      "rexe_amount": 40,
      "rexe_supply": 1000,
      "total-borrowed": 0,
      "rate": 0.005,
      "hourly-rate": 5.723443223443223e-7,
      "liabilities": 0,
      "timestamp": 1717276728
    },
    "REXE-2": {
      "index": 1,
      "rexe_amount": 0,
      "rexe_supply": 1000,
      "total-borrowed": 0,
      "rate": 0.005,
      "hourly-rate": 5.723443223443223e-7,
      "liabilities": 0,
      "timestamp": 1717276728
    }
  },
  {
    "USDT-0": {
      "index": 1,
      "usdt_amount": 193.11,
      "usdt_supply": 1000,
      "total-borrowed": 0,
      "rate": 0.005,
      "hourly-rate": 5.723443223443223e-7,
      "liabilities": 0,
      "timestamp": 1717276738,
      "liability_charge": 0
    },
    "USDT-1": {
      "index": 1,
      "usdt_amount": 806.89,
      "usdt_supply": 1000,
      "total-borrowed": 0,
      "rate": 0.005,
      "hourly-rate": 5.723443223443223e-7,
      "liabilities": 0,
      "timestamp": 1717276738,
      "earningreate_charge": 0
    },
    "USDT-2": {
      "index": 1,
      "usdt_amount": 0,
      "usdt_supply": 1000,
      "total-borrowed": 0,
      "rate": 0.005,
      "hourly-rate": 5.723443223443223e-7,
      "liabilities": 0,
      "timestamp": 1717276738
    },
    "REXE-0": {
      "index": 1,
      "rexe_amount": 959,
      "rexe_supply": 1000,
      "total-borrowed": 0,
      "rate": 0.005,
      "hourly-rate": 5.723443223443223e-7,
      "liabilities": 0,
      "timestamp": 1717276738
    },
    "REXE-1": {
      "index": 1,
      "rexe_amount": 41,
      "rexe_supply": 1000,
      "total-borrowed": 0,
      "rate": 0.005,
      "hourly-rate": 5.723443223443223e-7,
      "liabilities": 0,
      "timestamp": 1717276738
    },
    "REXE-2": {
      "index": 1,
      "rexe_amount": 0,
      "rexe_supply": 1000,
      "total-borrowed": 0,
      "rate": 0.005,
      "hourly-rate": 5.723443223443223e-7,
      "liabilities": 0,
      "timestamp": 1717276738
    }
  },
  {
    "USDT-0": {
      "index": 1,
      "usdt_amount": 197.82,
      "usdt_supply": 1000,
      "total-borrowed": 0,
      "rate": 0.005,
      "hourly-rate": 5.723443223443223e-7,
      "liabilities": 0,
      "timestamp": 1717276748,
      "liability_charge": 0
    },
    "USDT-1": {
      "index": 1,
      "usdt_amount": 802.18,
      "usdt_supply": 1000,
      "total-borrowed": 0,
      "rate": 0.005,
      "hourly-rate": 5.723443223443223e-7,
      "liabilities": 0,
      "timestamp": 1717276748,
      "earningreate_charge": 0
    },
    "USDT-2": {
      "index": 1,
      "usdt_amount": 0,
      "usdt_supply": 1000,
      "total-borrowed": 0,
      "rate": 0.005,
      "hourly-rate": 5.723443223443223e-7,
      "liabilities": 0,
      "timestamp": 1717276748
    },
    "REXE-0": {
      "index": 1,
      "rexe_amount": 958,
      "rexe_supply": 1000,
      "total-borrowed": 0,
      "rate": 0.005,
      "hourly-rate": 5.723443223443223e-7,
      "liabilities": 0,
      "timestamp": 1717276748
    },
    "REXE-1": {
      "index": 1,
      "rexe_amount": 42,
      "rexe_supply": 1000,
      "total-borrowed": 0,
      "rate": 0.005,
      "hourly-rate": 5.723443223443223e-7,
      "liabilities": 0,
      "timestamp": 1717276748
    },
    "REXE-2": {
      "index": 1,
      "rexe_amount": 0,
      "rexe_supply": 1000,
      "total-borrowed": 0,
      "rate": 0.005,
      "hourly-rate": 5.723443223443223e-7,
      "liabilities": 0,
      "timestamp": 1717276748
    }
  },
  {
    "USDT-0": {
      "index": 1,
      "usdt_amount": 202.53,
      "usdt_supply": 1000,
      "total-borrowed": 0,
      "rate": 0.005,
      "hourly-rate": 5.723443223443223e-7,
      "liabilities": 0,
      "timestamp": 1717276758,
      "liability_charge": 0
    },
    "USDT-1": {
      "index": 1,
      "usdt_amount": 797.47,
      "usdt_supply": 1000,
      "total-borrowed": 0,
      "rate": 0.005,
      "hourly-rate": 5.723443223443223e-7,
      "liabilities": 0,
      "timestamp": 1717276758,
      "earningreate_charge": 0
    },
    "USDT-2": {
      "index": 1,
      "usdt_amount": 0,
      "usdt_supply": 1000,
      "total-borrowed": 0,
      "rate": 0.005,
      "hourly-rate": 5.723443223443223e-7,
      "liabilities": 0,
      "timestamp": 1717276758
    },
    "REXE-0": {
      "index": 1,
      "rexe_amount": 957,
      "rexe_supply": 1000,
      "total-borrowed": 0,
      "rate": 0.005,
      "hourly-rate": 5.723443223443223e-7,
      "liabilities": 0,
      "timestamp": 1717276758
    },
    "REXE-1": {
      "index": 1,
      "rexe_amount": 43,
      "rexe_supply": 1000,
      "total-borrowed": 0,
      "rate": 0.005,
      "hourly-rate": 5.723443223443223e-7,
      "liabilities": 0,
      "timestamp": 1717276758
    },
    "REXE-2": {
      "index": 1,
      "rexe_amount": 0,
      "rexe_supply": 1000,
      "total-borrowed": 0,
      "rate": 0.005,
      "hourly-rate": 5.723443223443223e-7,
      "liabilities": 0,
      "timestamp": 1717276758
    }
  },
  {
    "USDT-0": {
      "index": 1,
      "usdt_amount": 207.24,
      "usdt_supply": 1000,
      "total-borrowed": 0,
      "rate": 0.005,
      "hourly-rate": 5.723443223443223e-7,
      "liabilities": 0,
      "timestamp": 1717276768,
      "liability_charge": 0
    },
    "USDT-1": {
      "index": 1,
      "usdt_amount": 792.76,
      "usdt_supply": 1000,
      "total-borrowed": 0,
      "rate": 0.005,
      "hourly-rate": 5.723443223443223e-7,
      "liabilities": 0,
      "timestamp": 1717276768,
      "earningreate_charge": 0
    },
    "USDT-2": {
      "index": 1,
      "usdt_amount": 0,
      "usdt_supply": 1000,
      "total-borrowed": 0,
      "rate": 0.005,
      "hourly-rate": 5.723443223443223e-7,
      "liabilities": 0,
      "timestamp": 1717276768
    },
    "REXE-0": {
      "index": 1,
      "rexe_amount": 956,
      "rexe_supply": 1000,
      "total-borrowed": 0,
      "rate": 0.005,
      "hourly-rate": 5.723443223443223e-7,
      "liabilities": 0,
      "timestamp": 1717276768
    },
    "REXE-1": {
      "index": 1,
      "rexe_amount": 44,
      "rexe_supply": 1000,
      "total-borrowed": 0,
      "rate": 0.005,
      "hourly-rate": 5.723443223443223e-7,
      "liabilities": 0,
      "timestamp": 1717276768
    },
    "REXE-2": {
      "index": 1,
      "rexe_amount": 0,
      "rexe_supply": 1000,
      "total-borrowed": 0,
      "rate": 0.005,
      "hourly-rate": 5.723443223443223e-7,
      "liabilities": 0,
      "timestamp": 1717276768
    }
  },
  {
    "USDT-0": {
      "index": 1,
      "usdt_amount": 211.95,
      "usdt_supply": 1000,
      "total-borrowed": 0,
      "rate": 0.005,
      "hourly-rate": 5.723443223443223e-7,
      "liabilities": 0,
      "timestamp": 1717276778,
      "liability_charge": 0
    },
    "USDT-1": {
      "index": 1,
      "usdt_amount": 788.05,
      "usdt_supply": 1000,
      "total-borrowed": 0,
      "rate": 0.005,
      "hourly-rate": 5.723443223443223e-7,
      "liabilities": 0,
      "timestamp": 1717276778,
      "earningreate_charge": 0
    },
    "USDT-2": {
      "index": 1,
      "usdt_amount": 0,
      "usdt_supply": 1000,
      "total-borrowed": 0,
      "rate": 0.005,
      "hourly-rate": 5.723443223443223e-7,
      "liabilities": 0,
      "timestamp": 1717276778
    },
    "REXE-0": {
      "index": 1,
      "rexe_amount": 955,
      "rexe_supply": 1000,
      "total-borrowed": 0,
      "rate": 0.005,
      "hourly-rate": 5.723443223443223e-7,
      "liabilities": 0,
      "timestamp": 1717276778
    },
    "REXE-1": {
      "index": 1,
      "rexe_amount": 45,
      "rexe_supply": 1000,
      "total-borrowed": 0,
      "rate": 0.005,
      "hourly-rate": 5.723443223443223e-7,
      "liabilities": 0,
      "timestamp": 1717276778
    },
    "REXE-2": {
      "index": 1,
      "rexe_amount": 0,
      "rexe_supply": 1000,
      "total-borrowed": 0,
      "rate": 0.005,
      "hourly-rate": 5.723443223443223e-7,
      "liabilities": 0,
      "timestamp": 1717276778
    }
  },
  {
    "USDT-0": {
      "index": 1,
      "usdt_amount": 216.66,
      "usdt_supply": 1000,
      "total-borrowed": 0,
      "rate": 0.005,
      "hourly-rate": 5.723443223443223e-7,
      "liabilities": 0,
      "timestamp": 1717276788,
      "liability_charge": 0
    },
    "USDT-1": {
      "index": 1,
      "usdt_amount": 783.34,
      "usdt_supply": 1000,
      "total-borrowed": 0,
      "rate": 0.005,
      "hourly-rate": 5.723443223443223e-7,
      "liabilities": 0,
      "timestamp": 1717276788,
      "earningreate_charge": 0
    },
    "USDT-2": {
      "index": 1,
      "usdt_amount": 0,
      "usdt_supply": 1000,
      "total-borrowed": 0,
      "rate": 0.005,
      "hourly-rate": 5.723443223443223e-7,
      "liabilities": 0,
      "timestamp": 1717276788
    },
    "REXE-0": {
      "index": 1,
      "rexe_amount": 954,
      "rexe_supply": 1000,
      "total-borrowed": 0,
      "rate": 0.005,
      "hourly-rate": 5.723443223443223e-7,
      "liabilities": 0,
      "timestamp": 1717276788
    },
    "REXE-1": {
      "index": 1,
      "rexe_amount": 46,
      "rexe_supply": 1000,
      "total-borrowed": 0,
      "rate": 0.005,
      "hourly-rate": 5.723443223443223e-7,
      "liabilities": 0,
      "timestamp": 1717276788
    },
    "REXE-2": {
      "index": 1,
      "rexe_amount": 0,
      "rexe_supply": 1000,
      "total-borrowed": 0,
      "rate": 0.005,
      "hourly-rate": 5.723443223443223e-7,
      "liabilities": 0,
      "timestamp": 1717276788
    }
  },
  {
    "USDT-0": {
      "index": 1,
      "usdt_amount": 221.37,
      "usdt_supply": 1000,
      "total-borrowed": 0,
      "rate": 0.005,
      "hourly-rate": 5.723443223443223e-7,
      "liabilities": 0,
      "timestamp": 1717276798,
      "liability_charge": 0
    },
    "USDT-1": {
      "index": 1,
      "usdt_amount": 778.6300000000001,
      "usdt_supply": 1000,
      "total-borrowed": 0,
      "rate": 0.005,
      "hourly-rate": 5.723443223443223e-7,
      "liabilities": 0,
      "timestamp": 1717276798,
      "earningreate_charge": 0
    },
    "USDT-2": {
      "index": 1,
      "usdt_amount": 0,
      "usdt_supply": 1000,
      "total-borrowed": 0,
      "rate": 0.005,
      "hourly-rate": 5.723443223443223e-7,
      "liabilities": 0,
      "timestamp": 1717276798
    },
    "REXE-0": {
      "index": 1,
      "rexe_amount": 953,
      "rexe_supply": 1000,
      "total-borrowed": 0,
      "rate": 0.005,
      "hourly-rate": 5.723443223443223e-7,
      "liabilities": 0,
      "timestamp": 1717276798
    },
    "REXE-1": {
      "index": 1,
      "rexe_amount": 47,
      "rexe_supply": 1000,
      "total-borrowed": 0,
      "rate": 0.005,
      "hourly-rate": 5.723443223443223e-7,
      "liabilities": 0,
      "timestamp": 1717276798
    },
    "REXE-2": {
      "index": 1,
      "rexe_amount": 0,
      "rexe_supply": 1000,
      "total-borrowed": 0,
      "rate": 0.005,
      "hourly-rate": 5.723443223443223e-7,
      "liabilities": 0,
      "timestamp": 1717276798
    }
  },
  {
    "USDT-0": {
      "index": 1,
      "usdt_amount": 226.08,
      "usdt_supply": 1000,
      "total-borrowed": 0,
      "rate": 0.005,
      "hourly-rate": 5.723443223443223e-7,
      "liabilities": 0,
      "timestamp": 1717276808,
      "liability_charge": 0
    },
    "USDT-1": {
      "index": 1,
      "usdt_amount": 773.92,
      "usdt_supply": 1000,
      "total-borrowed": 0,
      "rate": 0.005,
      "hourly-rate": 5.723443223443223e-7,
      "liabilities": 0,
      "timestamp": 1717276808,
      "earningreate_charge": 0
    },
    "USDT-2": {
      "index": 1,
      "usdt_amount": 0,
      "usdt_supply": 1000,
      "total-borrowed": 0,
      "rate": 0.005,
      "hourly-rate": 5.723443223443223e-7,
      "liabilities": 0,
      "timestamp": 1717276808
    },
    "REXE-0": {
      "index": 1,
      "rexe_amount": 952,
      "rexe_supply": 1000,
      "total-borrowed": 0,
      "rate": 0.005,
      "hourly-rate": 5.723443223443223e-7,
      "liabilities": 0,
      "timestamp": 1717276808
    },
    "REXE-1": {
      "index": 1,
      "rexe_amount": 48,
      "rexe_supply": 1000,
      "total-borrowed": 0,
      "rate": 0.005,
      "hourly-rate": 5.723443223443223e-7,
      "liabilities": 0,
      "timestamp": 1717276808
    },
    "REXE-2": {
      "index": 1,
      "rexe_amount": 0,
      "rexe_supply": 1000,
      "total-borrowed": 0,
      "rate": 0.005,
      "hourly-rate": 5.723443223443223e-7,
      "liabilities": 0,
      "timestamp": 1717276808
    }
  },
  {
    "USDT-0": {
      "index": 1,
      "usdt_amount": 230.79,
      "usdt_supply": 1000,
      "total-borrowed": 0,
      "rate": 0.005,
      "hourly-rate": 5.723443223443223e-7,
      "liabilities": 0,
      "timestamp": 1717276818,
      "liability_charge": 0
    },
    "USDT-1": {
      "index": 1,
      "usdt_amount": 769.2099999999999,
      "usdt_supply": 1000,
      "total-borrowed": 0,
      "rate": 0.005,
      "hourly-rate": 5.723443223443223e-7,
      "liabilities": 0,
      "timestamp": 1717276818,
      "earningreate_charge": 0
    },
    "USDT-2": {
      "index": 1,
      "usdt_amount": 0,
      "usdt_supply": 1000,
      "total-borrowed": 0,
      "rate": 0.005,
      "hourly-rate": 5.723443223443223e-7,
      "liabilities": 0,
      "timestamp": 1717276818
    },
    "REXE-0": {
      "index": 1,
      "rexe_amount": 951,
      "rexe_supply": 1000,
      "total-borrowed": 0,
      "rate": 0.005,
      "hourly-rate": 5.723443223443223e-7,
      "liabilities": 0,
      "timestamp": 1717276818
    },
    "REXE-1": {
      "index": 1,
      "rexe_amount": 49,
      "rexe_supply": 1000,
      "total-borrowed": 0,
      "rate": 0.005,
      "hourly-rate": 5.723443223443223e-7,
      "liabilities": 0,
      "timestamp": 1717276818
    },
    "REXE-2": {
      "index": 1,
      "rexe_amount": 0,
      "rexe_supply": 1000,
      "total-borrowed": 0,
      "rate": 0.005,
      "hourly-rate": 5.723443223443223e-7,
      "liabilities": 0,
      "timestamp": 1717276818
    }
  },
  {
    "USDT-0": {
      "index": 1,
      "usdt_amount": 235.5,
      "usdt_supply": 1000,
      "total-borrowed": 0,
      "rate": 0.005,
      "hourly-rate": 5.723443223443223e-7,
      "liabilities": 0,
      "timestamp": 1717276828,
      "liability_charge": 0
    },
    "USDT-1": {
      "index": 1,
      "usdt_amount": 764.5,
      "usdt_supply": 1000,
      "total-borrowed": 0,
      "rate": 0.005,
      "hourly-rate": 5.723443223443223e-7,
      "liabilities": 0,
      "timestamp": 1717276828,
      "earningreate_charge": 0
    },
    "USDT-2": {
      "index": 1,
      "usdt_amount": 0,
      "usdt_supply": 1000,
      "total-borrowed": 0,
      "rate": 0.005,
      "hourly-rate": 5.723443223443223e-7,
      "liabilities": 0,
      "timestamp": 1717276828
    },
    "REXE-0": {
      "index": 1,
      "rexe_amount": 950,
      "rexe_supply": 1000,
      "total-borrowed": 0,
      "rate": 0.005,
      "hourly-rate": 5.723443223443223e-7,
      "liabilities": 0,
      "timestamp": 1717276828
    },
    "REXE-1": {
      "index": 1,
      "rexe_amount": 50,
      "rexe_supply": 1000,
      "total-borrowed": 0,
      "rate": 0.005,
      "hourly-rate": 5.723443223443223e-7,
      "liabilities": 0,
      "timestamp": 1717276828
    },
    "REXE-2": {
      "index": 1,
      "rexe_amount": 0,
      "rexe_supply": 1000,
      "total-borrowed": 0,
      "rate": 0.005,
      "hourly-rate": 5.723443223443223e-7,
      "liabilities": 0,
      "timestamp": 1717276828
    }
  }
]